adamlibrary/adam.cpython-38-x86_64-linux-gnu.so
adamlibrary/datasetname.cpython-38-x86_64-linux-gnu.so
adamlibrary/math.cpython-38-x86_64-linux-gnu.so
adamlibrary/memreplication_cutline.cpython-38-x86_64-linux-gnu.so
adamlibrary/stringer.cpython-38-x86_64-linux-gnu.so
adamlibrary-1.6.1.dist-info/METADATA
adamlibrary-1.6.1.dist-info/WHEEL
adamlibrary-1.6.1.dist-info/top_level.txt
adamlibrary-1.6.1.dist-info/RECORD
