Metadata-Version: 2.1
Name: adamlibrary
Version: 1.6.1
Summary: Improved library for Python to support C library extensions
Home-page: UNKNOWN
License: UNKNOWN
Platform: UNKNOWN
Classifier: Programming Language :: Python :: 3
Classifier: Programming Language :: C
Classifier: Operating System :: OS Independent
Requires-Python: >=3.6
Requires-Dist: cython
Requires-Dist: setuptools
Requires-Dist: wheel
Requires-Dist: auditwheel
